{
  "$schema": "https://mintlify.com/docs.json",
  "theme": "mint",
  "name": "iCendant",
  "colors": {
    "primary": "#16A34A",
    "light": "#07C983",
    "dark": "#15803D"
  },
  "favicon": "/favicon.png",
  "navigation": {
    "tabs": [
      {
        "tab": "Guides",
        "groups": [
          {
            "group": "Get Started",
            "pages": [
              "introduction",
              "empathy",
              "author",
              "chat"
            ]
          }
        ]
      }
    ],
    "global": {
      "anchors": [
        {
          "anchor": "Documentation",
          "href": "./empathy-api-design",
          "icon": "book-open-cover"
        }
      ]
    }
  },
  "logo": {
    "light": "/logo/light.png",
    "dark": "/logo/dark.png"
  },
  "navbar": {
    "links": [
      {
        "label": "Support",
        "href": "mailto:hi@mintlify.com"
      },
      {
        "label": "Privacy Policy",
        "href": "./privacy"
      }
    ],
    "primary": {
      "type": "button",
      "label": "Dashboard",
      "href": "https://icendant.com/empathy"
    }
  },
  "footer": {
    
  }
}